pycrobot/__init__.py
pycrobot/bot.py
pybcrobot-0.1.0.dist-info/METADATA
pybcrobot-0.1.0.dist-info/WHEEL
pybcrobot-0.1.0.dist-info/top_level.txt
pybcrobot-0.1.0.dist-info/RECORD
